mdatagen/__init__.py
mdatagen/metrics/__init__.py
mdatagen/metrics/metric.py
mdatagen/multivariate/__init__.py
mdatagen/multivariate/mMAR.py
mdatagen/multivariate/mMCAR.py
mdatagen/multivariate/mMNAR.py
mdatagen/plots/__init__.py
mdatagen/plots/plot.py
mdatagen/univariate/__init__.py
mdatagen/univariate/uMAR.py
mdatagen/univariate/uMCAR.py
mdatagen/univariate/uMNAR.py
mdatagen/utils/__init__.py
mdatagen/utils/feature_choice.py
mdatagen/utils/math_calcs.py
mdatagen-0.2.0.dist-info/LICENSE
mdatagen-0.2.0.dist-info/METADATA
mdatagen-0.2.0.dist-info/WHEEL
mdatagen-0.2.0.dist-info/top_level.txt
mdatagen-0.2.0.dist-info/RECORD
