Metadata-Version: 2.1
Name: mdatagen
Version: 0.2.0
Summary: mdatagen: A Python Library for the Generation of Artificial Missing Data
Home-page: https://github.com/ArthurMangussi/pymdatagen
Author: Arthur Dantas Mangussi
Author-email: mangussiarthur@gmail.com
License: MIT
Keywords: machine learning,preprocessing data
Requires-Python: >=3.10.12
License-File: LICENSE
Requires-Dist: numpy>=1.25.0
Requires-Dist: pandas>=2.0.3
Requires-Dist: scikit-learn>=1.3.0
Requires-Dist: missingno>=0.5.2
Requires-Dist: scipy>=1.11.4
Requires-Dist: pyampute>=0.0.3
